libsoni/__init__.py
libsoni/utils.py
libsoni/version.py
libsoni/core/chroma.py
libsoni/core/f0.py
libsoni/core/methods.py
libsoni/core/pianoroll.py
libsoni/core/spectrogram.py
libsoni/core/tse.py
libsoni-1.1.0.dist-info/LICENSE
libsoni-1.1.0.dist-info/WHEEL
libsoni-1.1.0.dist-info/METADATA
libsoni-1.1.0.dist-info/RECORD
