Metadata-Version: 2.3
Name: libsoni
Version: 1.1.0
Summary: A Python toolbox for sonifying music annotations and feature representations
Author: Leo Brütting
Author-email: Yigitcan Özer <yigitcan.oezer@audiolabs-erlangen.de>, Simon Schwär <simon.schwaer@audiolabs-erlangen.de>, Meinard Müller <meinard.mueller@audiolabs-erlangen.de>
Requires-Python: >=3.7
Classifier: Development Status :: 4 - Beta
Classifier: Programming Language :: Python :: 3
Classifier: Intended Audience :: Developers
Classifier: License :: OSI Approved :: MIT License
Classifier: Topic :: Multimedia :: Sound/Audio :: Analysis
Requires-Dist: librosa >= 0.8.0
Requires-Dist: matplotlib >= 3.1.0
Requires-Dist: numpy >= 1.17.0
Requires-Dist: pandas >= 1.0.0
Requires-Dist: scipy >= 1.7.0
Requires-Dist: libfmp >= 1.2.0
Requires-Dist: flit >= 3.10.0 ; extra == "develop"
Requires-Dist: ipython >= 8.10.0 ; extra == "develop"
Requires-Dist: jupyter ; extra == "develop"
Requires-Dist: nbstripout ; extra == "develop"
Requires-Dist: sphinx ; extra == "doc"
Requires-Dist: sphinx_rtd_theme ; extra == "doc"
Requires-Dist: pytest ; extra == "test"
Requires-Dist: pytest-runner ; extra == "test"
Project-URL: Documentation, https://groupmm.github.io/libsoni/build/html/index.html
Project-URL: Homepage, https://github.com/groupmm/libsoni
Project-URL: Repository, https://github.com/groupmm/libsoni
Provides-Extra: develop
Provides-Extra: doc
Provides-Extra: test
